ajr/__init__.py
ajr/json_rpc.py
ajr-0.2.0.dist-info/METADATA
ajr-0.2.0.dist-info/RECORD
ajr-0.2.0.dist-info/WHEEL
ajr-0.2.0.dist-info/top_level.txt
