Metadata-Version: 2.1
Name: ajr
Version: 0.2.0
Summary: Asyncronous JSON-RPC router.
Home-page: https://bitbucket.org/closescreen/ajr/src/master/
Author: Close Screen
Author-email: close.screen@gmail.com
License: MIT
Project-URL: Source Code, https://bitbucket.org/closescreen/ajr/src/master/
Keywords: Async JSON-RPC AIOHTTP
Platform: UNKNOWN
Classifier: License :: OSI Approved :: MIT License
Classifier: Operating System :: POSIX :: Linux
Classifier: Programming Language :: Python :: 3.7
